avtk/__init__.py
avtk/backends/__init__.py
avtk/backends/ffmpeg/__init__.py
avtk/backends/ffmpeg/cap.py
avtk/backends/ffmpeg/convert.py
avtk/backends/ffmpeg/exceptions.py
avtk/backends/ffmpeg/probe.py
avtk/backends/ffmpeg/run.py
avtk/backends/ffmpeg/shortcuts.py
avtk-0.1.0.dist-info/LICENSE
avtk-0.1.0.dist-info/METADATA
avtk-0.1.0.dist-info/WHEEL
avtk-0.1.0.dist-info/top_level.txt
avtk-0.1.0.dist-info/RECORD
