Metadata-Version: 2.1
Name: avtk
Version: 0.1.0
Summary: Audio/Video toolkit
Home-page: https://github.com/senko/avtk
Author: Senko Rasic
Author-email: senko@senko.net
License: UNKNOWN
Platform: UNKNOWN
Classifier: Programming Language :: Python :: 3
Classifier: License :: OSI Approved :: MIT License
Classifier: Operating System :: OS Independent
